<annotation>
	<folder></folder>
	<filename>Kal4_1_ta_a_864_701_phone_pct_25_jpg.rf.17a96c9f23297cb7fa4b9f12de97d6d4.jpg</filename>
	<path>Kal4_1_ta_a_864_701_phone_pct_25_jpg.rf.17a96c9f23297cb7fa4b9f12de97d6d4.jpg</path>
	<source>
		<database>roboflow.ai</database>
	</source>
	<size>
		<width>720</width>
		<height>480</height>
		<depth>3</depth>
	</size>
	<segmented>0</segmented>
	<object>
		<name>-a-</name>
		<pose>Unspecified</pose>
		<truncated>0</truncated>
		<difficult>0</difficult>
		<occluded>0</occluded>
		<bndbox>
			<xmin>151</xmin>
			<xmax>623</xmax>
			<ymin>94</ymin>
			<ymax>378</ymax>
		</bndbox>
		<polygon>
			<x1>150</x1>
			<y1>193</y1>
			<x2>157</x2>
			<y2>202</y2>
			<x3>336</x3>
			<y3>377</y3>
			<x4>342</x4>
			<y4>376</y4>
			<x5>356</x5>
			<y5>366</y5>
			<x6>378</x6>
			<y6>360</y6>
			<x7>395</x7>
			<y7>360</y7>
			<x8>404</x8>
			<y8>362</y8>
			<x9>421</x9>
			<y9>369</y9>
			<x10>432</x10>
			<y10>377</y10>
			<x11>435</x11>
			<y11>377</y11>
			<x12>622</x12>
			<y12>193</y12>
			<x13>620</x13>
			<y13>188</y13>
			<x14>609</x14>
			<y14>178</y14>
			<x15>567</x15>
			<y15>146</y15>
			<x16>516</x16>
			<y16>119</y16>
			<x17>489</x17>
			<y17>109</y17>
			<x18>451</x18>
			<y18>99</y18>
			<x19>426</x19>
			<y19>95</y19>
			<x20>373</x20>
			<y20>93</y20>
			<x21>339</x21>
			<y21>96</y21>
			<x22>311</x22>
			<y22>101</y22>
			<x23>276</x23>
			<y23>111</y23>
			<x24>240</x24>
			<y24>126</y24>
			<x25>236</x25>
			<y25>130</y25>
			<x26>235</x26>
			<y26>185</y26>
			<x27>232</x27>
			<y27>187</y27>
			<x28>161</x28>
			<y28>186</y28>
			<x29>154</x29>
			<y29>187</y29>
		</polygon>
	</object>
	<object>
		<name>-a-</name>
		<pose>Unspecified</pose>
		<truncated>0</truncated>
		<difficult>0</difficult>
		<occluded>0</occluded>
		<bndbox>
			<xmin>152</xmin>
			<xmax>623</xmax>
			<ymin>95</ymin>
			<ymax>378</ymax>
		</bndbox>
		<polygon>
			<x1>151</x1>
			<y1>191</y1>
			<x2>151</x2>
			<y2>195</y2>
			<x3>336</x3>
			<y3>377</y3>
			<x4>342</x4>
			<y4>376</y4>
			<x5>356</x5>
			<y5>366</y5>
			<x6>378</x6>
			<y6>360</y6>
			<x7>395</x7>
			<y7>360</y7>
			<x8>416</x8>
			<y8>366</y8>
			<x9>430</x9>
			<y9>376</y9>
			<x10>435</x10>
			<y10>377</y10>
			<x11>622</x11>
			<y11>193</y11>
			<x12>611</x12>
			<y12>180</y12>
			<x13>588</x13>
			<y13>161</y13>
			<x14>567</x14>
			<y14>146</y14>
			<x15>525</x15>
			<y15>123</y15>
			<x16>492</x16>
			<y16>110</y16>
			<x17>459</x17>
			<y17>101</y17>
			<x18>426</x18>
			<y18>95</y18>
			<x19>366</x19>
			<y19>94</y19>
			<x20>326</x20>
			<y20>98</y20>
			<x21>299</x21>
			<y21>104</y21>
			<x22>257</x22>
			<y22>118</y22>
			<x23>240</x23>
			<y23>126</y23>
			<x24>236</x24>
			<y24>130</y24>
			<x25>236</x25>
			<y25>183</y25>
			<x26>234</x26>
			<y26>186</y26>
			<x27>218</x27>
			<y27>188</y27>
			<x28>209</x28>
			<y28>187</y28>
			<x29>206</x29>
			<y29>190</y29>
			<x30>202</x30>
			<y30>187</y30>
			<x31>181</x31>
			<y31>188</y31>
			<x32>166</x32>
			<y32>186</y32>
			<x33>155</x33>
			<y33>187</y33>
		</polygon>
	</object>
</annotation>
